{
  "schema_version": 1,
  "name": "guitarset-v1",
  "source": "Pitch-position counts built from the GuitarSet train split. Validation player is excluded so runtime loading does not require raw GuitarSet files.",
  "validation_player": "05",
  "training_tracks": 300,
  "alpha": 1.0,
  "power": 2.0,
  "counts": [
    [
      40,
      0,
      0,
      587
    ],
    [
      41,
      0,
      1,
      483
    ],
    [
      42,
      0,
      2,
      453
    ],
    [
      43,
      0,
      3,
      576
    ],
    [
      44,
      0,
      4,
      645
    ],
    [
      45,
      0,
      5,
      334
    ],
    [
      45,
      1,
      0,
      653
    ],
    [
      46,
      0,
      6,
      459
    ],
    [
      46,
      1,
      1,
      302
    ],
    [
      47,
      0,
      7,
      176
    ],
    [
      47,
      1,
      2,
      846
    ],
    [
      48,
      0,
      8,
      137
    ],
    [
      48,
      1,
      3,
      993
    ],
    [
      49,
      0,
      9,
      122
    ],
    [
      49,
      1,
      4,
      1389
    ],
    [
      50,
      0,
      10,
      75
    ],
    [
      50,
      1,
      5,
      652
    ],
    [
      50,
      2,
      0,
      691
    ],
    [
      51,
      0,
      11,
      6
    ],
    [
      51,
      1,
      6,
      1316
    ],
    [
      51,
      2,
      1,
      125
    ],
    [
      52,
      0,
      12,
      6
    ],
    [
      52,
      1,
      7,
      559
    ],
    [
      52,
      2,
      2,
      1070
    ],
    [
      53,
      1,
      8,
      675
    ],
    [
      53,
      2,
      3,
      1470
    ],
    [
      54,
      0,
      14,
      1
    ],
    [
      54,
      1,
      9,
      279
    ],
    [
      54,
      2,
      4,
      1233
    ],
    [
      55,
      1,
      10,
      161
    ],
    [
      55,
      2,
      5,
      1154
    ],
    [
      55,
      3,
      0,
      778
    ],
    [
      56,
      1,
      11,
      126
    ],
    [
      56,
      2,
      6,
      1943
    ],
    [
      56,
      3,
      1,
      577
    ],
    [
      57,
      1,
      12,
      68
    ],
    [
      57,
      2,
      7,
      1078
    ],
    [
      57,
      3,
      2,
      1067
    ],
    [
      58,
      2,
      8,
      1508
    ],
    [
      58,
      3,
      3,
      1261
    ],
    [
      59,
      2,
      9,
      639
    ],
    [
      59,
      3,
      4,
      1208
    ],
    [
      59,
      4,
      0,
      690
    ],
    [
      60,
      2,
      10,
      642
    ],
    [
      60,
      3,
      5,
      1177
    ],
    [
      60,
      4,
      1,
      663
    ],
    [
      61,
      2,
      11,
      321
    ],
    [
      61,
      3,
      6,
      1937
    ],
    [
      61,
      4,
      2,
      722
    ],
    [
      62,
      2,
      12,
      127
    ],
    [
      62,
      3,
      7,
      1453
    ],
    [
      62,
      4,
      3,
      995
    ],
    [
      63,
      2,
      13,
      70
    ],
    [
      63,
      3,
      8,
      1309
    ],
    [
      63,
      4,
      4,
      1095
    ],
    [
      64,
      2,
      14,
      8
    ],
    [
      64,
      3,
      9,
      885
    ],
    [
      64,
      4,
      5,
      933
    ],
    [
      64,
      5,
      0,
      529
    ],
    [
      65,
      2,
      15,
      1
    ],
    [
      65,
      3,
      10,
      706
    ],
    [
      65,
      4,
      6,
      1374
    ],
    [
      65,
      5,
      1,
      413
    ],
    [
      66,
      2,
      16,
      1
    ],
    [
      66,
      3,
      11,
      374
    ],
    [
      66,
      4,
      7,
      934
    ],
    [
      66,
      5,
      2,
      363
    ],
    [
      67,
      2,
      17,
      1
    ],
    [
      67,
      3,
      12,
      155
    ],
    [
      67,
      4,
      8,
      1209
    ],
    [
      67,
      5,
      3,
      502
    ],
    [
      68,
      2,
      18,
      5
    ],
    [
      68,
      3,
      13,
      111
    ],
    [
      68,
      4,
      9,
      737
    ],
    [
      68,
      5,
      4,
      650
    ],
    [
      69,
      2,
      19,
      3
    ],
    [
      69,
      3,
      14,
      20
    ],
    [
      69,
      4,
      10,
      589
    ],
    [
      69,
      5,
      5,
      611
    ],
    [
      70,
      3,
      15,
      32
    ],
    [
      70,
      4,
      11,
      367
    ],
    [
      70,
      5,
      6,
      686
    ],
    [
      71,
      3,
      16,
      3
    ],
    [
      71,
      4,
      12,
      203
    ],
    [
      71,
      5,
      7,
      352
    ],
    [
      72,
      3,
      17,
      2
    ],
    [
      72,
      4,
      13,
      196
    ],
    [
      72,
      5,
      8,
      633
    ],
    [
      73,
      3,
      18,
      2
    ],
    [
      73,
      4,
      14,
      44
    ],
    [
      73,
      5,
      9,
      326
    ],
    [
      74,
      4,
      15,
      37
    ],
    [
      74,
      5,
      10,
      271
    ],
    [
      75,
      4,
      16,
      25
    ],
    [
      75,
      5,
      11,
      136
    ],
    [
      76,
      4,
      17,
      3
    ],
    [
      76,
      5,
      12,
      120
    ],
    [
      77,
      5,
      13,
      78
    ],
    [
      78,
      4,
      19,
      2
    ],
    [
      78,
      5,
      14,
      26
    ],
    [
      79,
      5,
      15,
      8
    ],
    [
      80,
      5,
      16,
      12
    ],
    [
      81,
      5,
      17,
      1
    ]
  ]
}
